diffCheck/__init__.py
diffCheck/df_cvt_bindings.py
diffCheck/df_error_estimation.py
diffCheck/df_geometries.py
diffCheck/df_joint_detector.py
diffCheck/df_transformations.py
diffCheck/df_util.py
diffCheck/df_visualization.py
diffCheck/diffcheck_bindings.cp39-win_amd64.pyd
diffCheck/dlls/Open3D.dll
diffCheck/dlls/diffCheck.dll
diffcheck-1.3.1.dist-info/METADATA
diffcheck-1.3.1.dist-info/WHEEL
diffcheck-1.3.1.dist-info/top_level.txt
diffcheck-1.3.1.dist-info/RECORD
