Metadata-Version: 2.4
Name: diffCheck
Version: 1.3.1
Summary: DiffCheck is a package to check the differences between two timber structures
Home-page: https://github.com/diffCheckOrg/diffCheck
Author: Andrea Settimi, Damien Gilliard, Eleni Skevaki, Marirena Kladeftira, Julien Gamerro, Stefana Parascho, and Yves Weinand
Author-email: andrea.settimi@epfl.ch
Classifier: License :: OSI Approved :: MIT License
Classifier: Programming Language :: Python :: 3
Classifier: Programming Language :: Python :: 3.9
Requires-Dist: numpy
Requires-Dist: pybind11>=2.5.0
Dynamic: author
Dynamic: author-email
Dynamic: classifier
Dynamic: description
Dynamic: description-content-type
Dynamic: home-page
Dynamic: requires-dist
Dynamic: summary
